raia/__init__.py
raia/emoji.py
raia/rgb.py
raia-0.4.2.dist-info/LICENSE
raia-0.4.2.dist-info/METADATA
raia-0.4.2.dist-info/WHEEL
raia-0.4.2.dist-info/top_level.txt
raia-0.4.2.dist-info/RECORD
