Metadata-Version: 2.2
Name: raia
Version: 0.4.2
Summary: Simplistic python package to print colored and/or styled text with a user friendly API.
Home-page: https://github.com/AlexStratou/raia
Download-URL: https://github.com/AlexStratou/raia/archive/refs/tags/v0.4.2.zip
Author: Alexandros Stratoudakis
Author-email: alexstrat4@gmail.com
License: MIT
Classifier: Development Status :: 3 - Alpha
Classifier: Environment :: Console
Classifier: Intended Audience :: Developers
Classifier: License :: OSI Approved :: MIT License
Classifier: Operating System :: OS Independent
Classifier: Programming Language :: Python :: 3.10
Classifier: Programming Language :: Python :: 3.11
Classifier: Programming Language :: Python :: 3.12
Classifier: Topic :: Software Development :: Libraries :: Python Modules
Requires-Python: >=3.10
License-File: LICENSE
Dynamic: author
Dynamic: author-email
Dynamic: classifier
Dynamic: description
Dynamic: description-content-type
Dynamic: download-url
Dynamic: home-page
Dynamic: license
Dynamic: requires-python
Dynamic: summary
